djsms/__init__.py
djsms/apps.py
djsms/conf.py
djsms/consts.py
djsms/errors.py
djsms/hooks.py
djsms/models.py
djsms/request.py
djsms/backends/__init__.py
djsms/backends/base.py
djsms/backends/ippanel.py
djsms/backends/melipayamak.py
djsms/migrations/0001_initial.py
djsms/migrations/0002_remove_message_backend_remove_message_text.py
djsms/migrations/0003_message_data_message_recipient_message_text.py
djsms/migrations/__init__.py
djsms-0.0.6.dist-info/licenses/LICENSE
djsms-0.0.6.dist-info/METADATA
djsms-0.0.6.dist-info/WHEEL
djsms-0.0.6.dist-info/top_level.txt
djsms-0.0.6.dist-info/RECORD
